Metadata-Version: 2.1
Name: tgcodes
Version: 0.1.2
Summary: API Client for https://gateway.telegram.org/.
Home-page: https://github.com/nesquikcode/TGCodes
Author: nesquikcode
Author-email: nesquik@nishine.ru
License: MIT
License-File: LICENSE
Requires-Dist: requests
